tai_aws_account_bootstrap/__init__.py
tai_aws_account_bootstrap/base_stack.py
tai_aws_account_bootstrap/bootstrap_stack.py
tai_aws_account_bootstrap/stack_config_models.py
tai_aws_account_bootstrap/stack_helpers.py
tai_aws_account_bootstrap-0.0.1.dist-info/METADATA
tai_aws_account_bootstrap-0.0.1.dist-info/WHEEL
tai_aws_account_bootstrap-0.0.1.dist-info/RECORD
